__init__.py
wpApi.py
wordprest-0.0.4.dist-info/licenses/LICENSE
wordprest-0.0.4.dist-info/METADATA
wordprest-0.0.4.dist-info/WHEEL
wordprest-0.0.4.dist-info/top_level.txt
wordprest-0.0.4.dist-info/RECORD
