Metadata-Version: 2.4
Name: WordPResT
Version: 0.0.4
Summary: A simple wordpress api
Author-email: Ishaga Bello <bello@bellodoesseo.com>
License-Expression: MIT
Project-URL: Homepage, https://github.com/ishaga-bello/Wordpress-API
Project-URL: Issues, https://github.com/ishaga-bello/Wordpress-API/issues
Classifier: Programming Language :: Python :: 3
Classifier: Operating System :: OS Independent
Requires-Python: >=3.8
License-File: LICENSE
Dynamic: license-file
